{
  "project_info": {
    "project_number": "1087778694235",
    "project_id": "flutterwithfirebaseow",
    "storage_bucket": "flutterwithfirebaseow.appspot.com"
  },
  "client": [
    {
      "client_info": {
        "mobilesdk_app_id": "1:1087778694235:android:dd5cdf8b2b03d65bf30b7e",
        "android_client_info": {
          "package_name": "com.example.flutter_with_firebase"
        }
      },
      "oauth_client": [
        {
          "client_id": "1087778694235-vv8vbmnl6pn453ltiqftuudmv56r4rm4.apps.googleusercontent.com",
          "client_type": 3
        }
      ],
      "api_key": [
        {
          "current_key": "AIzaSyCk_QegU6jAQpMVZAO92OgTrhZe80w3ToM"
        }
      ],
      "services": {
        "appinvite_service": {
          "other_platform_oauth_client": [
            {
              "client_id": "1087778694235-vv8vbmnl6pn453ltiqftuudmv56r4rm4.apps.googleusercontent.com",
              "client_type": 3
            },
            {
              "client_id": "1087778694235-c81tb6nps4km7bmbufhq5cnb8ivattdm.apps.googleusercontent.com",
              "client_type": 2,
              "ios_info": {
                "bundle_id": "com.example.flutterWithFirebase"
              }
            }
          ]
        }
      }
    },
    {
      "client_info": {
        "mobilesdk_app_id": "1:1087778694235:android:64ba252e0d9f97f3f30b7e",
        "android_client_info": {
          "package_name": "com.example.flutterwithfirebaseOw"
        }
      },
      "oauth_client": [
        {
          "client_id": "1087778694235-delcjq7smo0ki2hor3pfqbf73fmrltjf.apps.googleusercontent.com",
          "client_type": 1,
          "android_info": {
            "package_name": "com.example.flutterwithfirebaseOw",
            "certificate_hash": "347ac74c923b2b6795b163b85fce89bbf2674268"
          }
        },
        {
          "client_id": "1087778694235-vv8vbmnl6pn453ltiqftuudmv56r4rm4.apps.googleusercontent.com",
          "client_type": 3
        }
      ],
      "api_key": [
        {
          "current_key": "AIzaSyCk_QegU6jAQpMVZAO92OgTrhZe80w3ToM"
        }
      ],
      "services": {
        "appinvite_service": {
          "other_platform_oauth_client": [
            {
              "client_id": "1087778694235-vv8vbmnl6pn453ltiqftuudmv56r4rm4.apps.googleusercontent.com",
              "client_type": 3
            },
            {
              "client_id": "1087778694235-c81tb6nps4km7bmbufhq5cnb8ivattdm.apps.googleusercontent.com",
              "client_type": 2,
              "ios_info": {
                "bundle_id": "com.example.flutterWithFirebase"
              }
            }
          ]
        }
      }
    }
  ],
  "configuration_version": "1"
}